{"title":"KBS연예 ─ KBS","url":"https://kstar.kbs.co.kr/list.html?cate=BC","favicon":"https://kstar.kbs.co.kr/favicon.ico","elements":[{"title":"‘불후의 명곡 - 송골매 편' 사거리 그오빠 지현우","contents":"<a href=\"https://kstar.kbs.co.kr/list_view.html?idx=223772\">\t<span class=\"img-box hh\">\n\t\t<span class=\"img-thum\">\n\t\t\t<span class=\"img-center\">\n\t\t\t\t<img src=\"https://entertainimg.kbsmedia.co.kr/cms/uploads/CONTENTS_20220813131049_e6c667a1bd893e5820d162e8f6a04b06.jpg\" alt=\"대체 텍스트\">\n\t\t\t</span>\n\t\t</span>\n\t</span></a>\n\t<span class=\"txt\">\n\t\t<span class=\"max-progtit\"><a href=\"https://kstar.kbs.co.kr/list_view.html?idx=223772\">‘불후의 명곡 - 송골매 편' 사거리 그오빠 지현우</a></span>\n\t\t<em class=\"prog\"><a href=\"https://kstar.kbs.co.kr/list.html?program_title=%EB%B6%88%ED%9B%84%EC%9D%98%20%EB%AA%85%EA%B3%A1\">불후의 명곡</a></em>\n\t</span>","link":"https://kstar.kbs.co.kr/list_view.html?idx=223772","retrieved":1660364061519,"image":"https://entertainimg.kbsmedia.co.kr/cms/uploads/CONTENTS_20220813131049_e6c667a1bd893e5820d162e8f6a04b06.jpg"},{"title":"'법대로 사랑하라' 명품조연 \"장혜진-백현주x이민영x전노민x조한철-전국환\"","contents":"<a href=\"https://kstar.kbs.co.kr/list_view.html?idx=223629\">\t<span class=\"img-box hh\">\n\t\t<span class=\"img-thum\">\n\t\t\t<span class=\"img-center\">\n\t\t\t\t<img src=\"https://entertainimg.kbsmedia.co.kr/cms/uploads/CONTENTS_20220812143907_24b2cba7e839c93d331a8718d557d978.jpg\" alt=\"대체 텍스트\">\n\t\t\t</span>\n\t\t</span>\n\t</span></a>\n\t<span class=\"txt\">\n\t\t<span class=\"max-progtit\"><a href=\"https://kstar.kbs.co.kr/list_view.html?idx=223629\">'법대로 사랑하라' 명품조연 \"장혜진-백현주x이민영x전노민x조한철-전국환\"</a></span>\n\t\t<em class=\"prog\"><a href=\"https://kstar.kbs.co.kr/list.html?program_title=%EC%9B%94%ED%99%94%EB%93%9C%EB%9D%BC%EB%A7%88%20%EB%B2%95%EB%8C%80%EB%A1%9C%20%EC%82%AC%EB%9E%91%ED%95%98%EB%9D%BC\">월화드라마 법대로 사랑하라</a></em>\n\t</span>","link":"https://kstar.kbs.co.kr/list_view.html?idx=223629","retrieved":1660345397792,"image":"https://entertainimg.kbsmedia.co.kr/cms/uploads/CONTENTS_20220812143907_24b2cba7e839c93d331a8718d557d978.jpg"},{"title":"[신상출시 편스토랑] 류수영, MZ세대의 입맛을 사로잡을 <로제 부대찌개> 탄생!","contents":"<a href=\"https://kstar.kbs.co.kr/list_view.html?idx=223742\">\t<span class=\"img-box ww\">\n\t\t<span class=\"img-thum\">\n\t\t\t<span class=\"img-center\">\n\t\t\t\t<img src=\"https://entertainimg.kbsmedia.co.kr/cms/uploads/CONTENTS_20220813001739_4284c3772183adcac448278a8cccd8f5_1.PNG\" alt=\"대체 텍스트\">\n\t\t\t</span>\n\t\t</span>\n\t</span></a>\n\t<span class=\"txt\">\n\t\t<span class=\"max-progtit\"><a href=\"https://kstar.kbs.co.kr/list_view.html?idx=223742\">[신상출시 편스토랑] 류수영, MZ세대의 입맛을 사로잡을 &lt;로제 부대찌개&gt; 탄생! </a></span>\n\t\t<em class=\"prog\"><a href=\"https://kstar.kbs.co.kr/list.html?program_title=%EC%8B%A0%EC%83%81%20%EC%B6%9C%EC%8B%9C%20%ED%8E%B8%EC%8A%A4%ED%86%A0%EB%9E%91\">신상 출시 편스토랑</a></em>\n\t</span>","link":"https://kstar.kbs.co.kr/list_view.html?idx=223742","retrieved":1660320551699,"image":"https://entertainimg.kbsmedia.co.kr/cms/uploads/CONTENTS_20220813001739_4284c3772183adcac448278a8cccd8f5_1.PNG"},{"title":"[신상출시 편스토랑] 박재범, 메뉴의 상품성에 극찬을 쏟아낸 스페셜 평가단 대표★","contents":"<a href=\"https://kstar.kbs.co.kr/list_view.html?idx=223738\">\t<span class=\"img-box ww\">\n\t\t<span class=\"img-thum\">\n\t\t\t<span class=\"img-center\">\n\t\t\t\t<img src=\"https://entertainimg.kbsmedia.co.kr/cms/uploads/CONTENTS_20220813001539_1ee1cdbdeec75a96170a6dc6aa513765_1.PNG\" alt=\"대체 텍스트\">\n\t\t\t</span>\n\t\t</span>\n\t</span></a>\n\t<span class=\"txt\">\n\t\t<span class=\"max-progtit\"><a href=\"https://kstar.kbs.co.kr/list_view.html?idx=223738\">[신상출시 편스토랑] 박재범, 메뉴의 상품성에 극찬을 쏟아낸 스페셜 평가단 대표★</a></span>\n\t\t<em class=\"prog\"><a href=\"https://kstar.kbs.co.kr/list.html?program_title=%EC%8B%A0%EC%83%81%20%EC%B6%9C%EC%8B%9C%20%ED%8E%B8%EC%8A%A4%ED%86%A0%EB%9E%91\">신상 출시 편스토랑</a></em>\n\t</span>","link":"https://kstar.kbs.co.kr/list_view.html?idx=223738","retrieved":1660320551724,"image":"https://entertainimg.kbsmedia.co.kr/cms/uploads/CONTENTS_20220813001539_1ee1cdbdeec75a96170a6dc6aa513765_1.PNG"},{"title":"[신상출시 편스토랑] 차예련, 애주가 주상욱이 반한 안주 메뉴로 우승을 차지할 수 있을까?","contents":"<a href=\"https://kstar.kbs.co.kr/list_view.html?idx=223734\">\t<span class=\"img-box ww\">\n\t\t<span class=\"img-thum\">\n\t\t\t<span class=\"img-center\">\n\t\t\t\t<img src=\"https://entertainimg.kbsmedia.co.kr/cms/uploads/CONTENTS_20220813001349_23ad8f5531831bf0e520be43b0eee099.PNG\" alt=\"대체 텍스트\">\n\t\t\t</span>\n\t\t</span>\n\t</span></a>\n\t<span class=\"txt\">\n\t\t<span class=\"max-progtit\"><a href=\"https://kstar.kbs.co.kr/list_view.html?idx=223734\">[신상출시 편스토랑] 차예련, 애주가 주상욱이 반한 안주 메뉴로 우승을 차지할 수 있을까?</a></span>\n\t\t<em class=\"prog\"><a href=\"https://kstar.kbs.co.kr/list.html?program_title=%EC%8B%A0%EC%83%81%20%EC%B6%9C%EC%8B%9C%20%ED%8E%B8%EC%8A%A4%ED%86%A0%EB%9E%91\">신상 출시 편스토랑</a></em>\n\t</span>","link":"https://kstar.kbs.co.kr/list_view.html?idx=223734","retrieved":1660320551726,"image":"https://entertainimg.kbsmedia.co.kr/cms/uploads/CONTENTS_20220813001349_23ad8f5531831bf0e520be43b0eee099.PNG"},{"title":"[신상출시 편스토랑] ※주목※ 막창 맛집의 아들 이찬원, 아낌없는 영업비밀 공개!","contents":"<a href=\"https://kstar.kbs.co.kr/list_view.html?idx=223730\">\t<span class=\"img-box ww\">\n\t\t<span class=\"img-thum\">\n\t\t\t<span class=\"img-center\">\n\t\t\t\t<img src=\"https://entertainimg.kbsmedia.co.kr/cms/uploads/CONTENTS_20220812234115_668a41a45a9d1e7c23b70e94e9461fc6_1.PNG\" alt=\"대체 텍스트\">\n\t\t\t</span>\n\t\t</span>\n\t</span></a>\n\t<span class=\"txt\">\n\t\t<span class=\"max-progtit\"><a href=\"https://kstar.kbs.co.kr/list_view.html?idx=223730\">[신상출시 편스토랑] ※주목※ 막창 맛집의 아들 이찬원, 아낌없는 영업비밀 공개!</a></span>\n\t\t<em class=\"prog\"><a href=\"https://kstar.kbs.co.kr/list.html?program_title=%EC%8B%A0%EC%83%81%20%EC%B6%9C%EC%8B%9C%20%ED%8E%B8%EC%8A%A4%ED%86%A0%EB%9E%91\">신상 출시 편스토랑</a></em>\n\t</span>","link":"https://kstar.kbs.co.kr/list_view.html?idx=223730","retrieved":1660320551730,"image":"https://entertainimg.kbsmedia.co.kr/cms/uploads/CONTENTS_20220812234115_668a41a45a9d1e7c23b70e94e9461fc6_1.PNG"},{"title":"[서울페스타 2022] 그룹 네이처(NATURE), 축제 분위기를 한껏 더 높이는 흥겨운 무대","contents":"<a href=\"https://kstar.kbs.co.kr/list_view.html?idx=223726\">\t<span class=\"img-box ww\">\n\t\t<span class=\"img-thum\">\n\t\t\t<span class=\"img-center\">\n\t\t\t\t<img src=\"https://entertainimg.kbsmedia.co.kr/cms/uploads/CONTENTS_20220812233753_21858059baf40cd43cc6d2b85886f530_1.PNG\" alt=\"대체 텍스트\">\n\t\t\t</span>\n\t\t</span>\n\t</span></a>\n\t<span class=\"txt\">\n\t\t<span class=\"max-progtit\"><a href=\"https://kstar.kbs.co.kr/list_view.html?idx=223726\">[서울페스타 2022] 그룹 네이처(NATURE), 축제 분위기를 한껏 더 높이는 흥겨운 무대</a></span>\n\t\t<em class=\"prog\"><a href=\"https://kstar.kbs.co.kr/list.html?program_title=%EC%84%9C%EC%9A%B8%20%ED%8E%98%EC%8A%A4%ED%83%80%202022%20%EA%B0%9C%EB%A7%89%EA%B3%B5%EC%97%B0\">서울 페스타 2022 개막공연</a></em>\n\t</span>","link":"https://kstar.kbs.co.kr/list_view.html?idx=223726","retrieved":1660320551731,"image":"https://entertainimg.kbsmedia.co.kr/cms/uploads/CONTENTS_20220812233753_21858059baf40cd43cc6d2b85886f530_1.PNG"},{"title":"[서울페스타 2022] K-POP 슈퍼 라이브 공연에서 멋진 무대를 선보이는 가수 비","contents":"<a href=\"https://kstar.kbs.co.kr/list_view.html?idx=223722\">\t<span class=\"img-box ww\">\n\t\t<span class=\"img-thum\">\n\t\t\t<span class=\"img-center\">\n\t\t\t\t<img src=\"https://entertainimg.kbsmedia.co.kr/cms/uploads/CONTENTS_20220812233033_c29fbf0e83925fbbef3c87755661e0b6.PNG\" alt=\"대체 텍스트\">\n\t\t\t</span>\n\t\t</span>\n\t</span></a>\n\t<span class=\"txt\">\n\t\t<span class=\"max-progtit\"><a href=\"https://kstar.kbs.co.kr/list_view.html?idx=223722\">[서울페스타 2022] K-POP 슈퍼 라이브 공연에서 멋진 무대를 선보이는 가수 비</a></span>\n\t\t<em class=\"prog\"><a href=\"https://kstar.kbs.co.kr/list.html?program_title=%EC%84%9C%EC%9A%B8%20%ED%8E%98%EC%8A%A4%ED%83%80%202022%20%EA%B0%9C%EB%A7%89%EA%B3%B5%EC%97%B0\">서울 페스타 2022 개막공연</a></em>\n\t</span>","link":"https://kstar.kbs.co.kr/list_view.html?idx=223722","retrieved":1660320551732,"image":"https://entertainimg.kbsmedia.co.kr/cms/uploads/CONTENTS_20220812233033_c29fbf0e83925fbbef3c87755661e0b6.PNG"},{"title":"[서울페스타 2022] 가수 싸이, 다함께 즐겨요 ♪준비하시고 쏘세요 ‘That That’","contents":"<a href=\"https://kstar.kbs.co.kr/list_view.html?idx=223718\">\t<span class=\"img-box ww\">\n\t\t<span class=\"img-thum\">\n\t\t\t<span class=\"img-center\">\n\t\t\t\t<img src=\"https://entertainimg.kbsmedia.co.kr/cms/uploads/CONTENTS_20220812232149_d82c35f91eea53120da7d5cb1fac96f8_1.PNG\" alt=\"대체 텍스트\">\n\t\t\t</span>\n\t\t</span>\n\t</span></a>\n\t<span class=\"txt\">\n\t\t<span class=\"max-progtit\"><a href=\"https://kstar.kbs.co.kr/list_view.html?idx=223718\">[서울페스타 2022] 가수 싸이, 다함께 즐겨요 ♪준비하시고 쏘세요 ‘That That’</a></span>\n\t\t<em class=\"prog\"><a href=\"https://kstar.kbs.co.kr/list.html?program_title=%EC%84%9C%EC%9A%B8%20%ED%8E%98%EC%8A%A4%ED%83%80%202022%20%EA%B0%9C%EB%A7%89%EA%B3%B5%EC%97%B0\">서울 페스타 2022 개막공연</a></em>\n\t</span>","link":"https://kstar.kbs.co.kr/list_view.html?idx=223718","retrieved":1660320551733,"image":"https://entertainimg.kbsmedia.co.kr/cms/uploads/CONTENTS_20220812232149_d82c35f91eea53120da7d5cb1fac96f8_1.PNG"},{"title":"[서울페스타 2022] 남성 4중창 보컬 그룹 포레스텔라, 오프닝 공연 ‘Champions’","contents":"<a href=\"https://kstar.kbs.co.kr/list_view.html?idx=223714\">\t<span class=\"img-box ww\">\n\t\t<span class=\"img-thum\">\n\t\t\t<span class=\"img-center\">\n\t\t\t\t<img src=\"https://entertainimg.kbsmedia.co.kr/cms/uploads/CONTENTS_20220812230706_8b331590f374085af3148573f7537399_1.PNG\" alt=\"대체 텍스트\">\n\t\t\t</span>\n\t\t</span>\n\t</span></a>\n\t<span class=\"txt\">\n\t\t<span class=\"max-progtit\"><a href=\"https://kstar.kbs.co.kr/list_view.html?idx=223714\">[서울페스타 2022] 남성 4중창 보컬 그룹 포레스텔라, 오프닝 공연 ‘Champions’</a></span>\n\t\t<em class=\"prog\"><a href=\"https://kstar.kbs.co.kr/list.html?program_title=%EC%84%9C%EC%9A%B8%20%ED%8E%98%EC%8A%A4%ED%83%80%202022%20%EA%B0%9C%EB%A7%89%EA%B3%B5%EC%97%B0\">서울 페스타 2022 개막공연</a></em>\n\t</span>","link":"https://kstar.kbs.co.kr/list_view.html?idx=223714","retrieved":1660313253442,"image":"https://entertainimg.kbsmedia.co.kr/cms/uploads/CONTENTS_20220812230706_8b331590f374085af3148573f7537399_1.PNG"},{"title":"[뮤직뱅크] 골든차일드, 전 세계를 뒤흔든 카리스마! 강렬한 AURA 로 컴백 ♪Replay","contents":"<a href=\"https://kstar.kbs.co.kr/list_view.html?idx=223709\">\t<span class=\"img-box ww\">\n\t\t<span class=\"img-thum\">\n\t\t\t<span class=\"img-center\">\n\t\t\t\t<img src=\"https://entertainimg.kbsmedia.co.kr/cms/uploads/CONTENTS_20220812221402_62e07a794e84e1361c383ee8408357f1_1.PNG\" alt=\"대체 텍스트\">\n\t\t\t</span>\n\t\t</span>\n\t</span></a>\n\t<span class=\"txt\">\n\t\t<span class=\"max-progtit\"><a href=\"https://kstar.kbs.co.kr/list_view.html?idx=223709\">[뮤직뱅크] 골든차일드, 전 세계를 뒤흔든 카리스마! 강렬한 AURA 로 컴백 ♪Replay</a></span>\n\t\t<em class=\"prog\"><a href=\"https://kstar.kbs.co.kr/list.html?program_title=%EB%AE%A4%EC%A7%81%EB%B1%85%ED%81%AC\">뮤직뱅크</a></em>\n\t</span>","link":"https://kstar.kbs.co.kr/list_view.html?idx=223709","retrieved":1660311176025,"image":"https://entertainimg.kbsmedia.co.kr/cms/uploads/CONTENTS_20220812221402_62e07a794e84e1361c383ee8408357f1_1.PNG"},{"title":"[뮤직뱅크] 흘러넘치는 청량 매력~ 코요테와 어디든 가보자 ♪GO","contents":"<a href=\"https://kstar.kbs.co.kr/list_view.html?idx=223705\">\t<span class=\"img-box ww\">\n\t\t<span class=\"img-thum\">\n\t\t\t<span class=\"img-center\">\n\t\t\t\t<img src=\"https://entertainimg.kbsmedia.co.kr/cms/uploads/CONTENTS_20220812220413_a8e6365a92f39d67cd77c572ce7086c6.PNG\" alt=\"대체 텍스트\">\n\t\t\t</span>\n\t\t</span>\n\t</span></a>\n\t<span class=\"txt\">\n\t\t<span class=\"max-progtit\"><a href=\"https://kstar.kbs.co.kr/list_view.html?idx=223705\">[뮤직뱅크] 흘러넘치는 청량 매력~ 코요테와 어디든 가보자 ♪GO</a></span>\n\t\t<em class=\"prog\"><a href=\"https://kstar.kbs.co.kr/list.html?program_title=%EB%AE%A4%EC%A7%81%EB%B1%85%ED%81%AC\">뮤직뱅크</a></em>\n\t</span>","link":"https://kstar.kbs.co.kr/list_view.html?idx=223705","retrieved":1660311176026,"image":"https://entertainimg.kbsmedia.co.kr/cms/uploads/CONTENTS_20220812220413_a8e6365a92f39d67cd77c572ce7086c6.PNG"},{"title":"[뮤직뱅크] ATEEZ(에이티즈), 2주 연속 1위의 영광! 음악방송 6관왕 ♪Guerrilla","contents":"<a href=\"https://kstar.kbs.co.kr/list_view.html?idx=223701\">\t<span class=\"img-box ww\">\n\t\t<span class=\"img-thum\">\n\t\t\t<span class=\"img-center\">\n\t\t\t\t<img src=\"https://entertainimg.kbsmedia.co.kr/cms/uploads/CONTENTS_20220812213423_edecae142bc69babeb9ca4f7b713ddd8_1.PNG\" alt=\"대체 텍스트\">\n\t\t\t</span>\n\t\t</span>\n\t</span></a>\n\t<span class=\"txt\">\n\t\t<span class=\"max-progtit\"><a href=\"https://kstar.kbs.co.kr/list_view.html?idx=223701\">[뮤직뱅크] ATEEZ(에이티즈), 2주 연속 1위의 영광! 음악방송 6관왕 ♪Guerrilla</a></span>\n\t\t<em class=\"prog\"><a href=\"https://kstar.kbs.co.kr/list.html?program_title=%EB%AE%A4%EC%A7%81%EB%B1%85%ED%81%AC\">뮤직뱅크</a></em>\n\t</span>","link":"https://kstar.kbs.co.kr/list_view.html?idx=223701","retrieved":1660311176026,"image":"https://entertainimg.kbsmedia.co.kr/cms/uploads/CONTENTS_20220812213423_edecae142bc69babeb9ca4f7b713ddd8_1.PNG"},{"title":"[뮤직뱅크] 대세 그룹 뉴진스, 10대 특유의 순수하고 자연스러운 매력 발산 ♪Attention","contents":"<a href=\"https://kstar.kbs.co.kr/list_view.html?idx=223697\">\t<span class=\"img-box ww\">\n\t\t<span class=\"img-thum\">\n\t\t\t<span class=\"img-center\">\n\t\t\t\t<img src=\"https://entertainimg.kbsmedia.co.kr/cms/uploads/CONTENTS_20220812211629_feed3c030aeaad9b60568ea12e087958.PNG\" alt=\"대체 텍스트\">\n\t\t\t</span>\n\t\t</span>\n\t</span></a>\n\t<span class=\"txt\">\n\t\t<span class=\"max-progtit\"><a href=\"https://kstar.kbs.co.kr/list_view.html?idx=223697\">[뮤직뱅크] 대세 그룹 뉴진스, 10대 특유의 순수하고 자연스러운 매력 발산 ♪Attention</a></span>\n\t\t<em class=\"prog\"><a href=\"https://kstar.kbs.co.kr/list.html?program_title=%EB%AE%A4%EC%A7%81%EB%B1%85%ED%81%AC\">뮤직뱅크</a></em>\n\t</span>","link":"https://kstar.kbs.co.kr/list_view.html?idx=223697","retrieved":1660311176026,"image":"https://entertainimg.kbsmedia.co.kr/cms/uploads/CONTENTS_20220812211629_feed3c030aeaad9b60568ea12e087958.PNG"},{"title":"[독립영화관] '습도 다소 높음' 고봉수 스타일을 아시나요 (고봉수 감독,2021)","contents":"<a href=\"https://kstar.kbs.co.kr/list_view.html?idx=223686\">\t<span class=\"img-box hh\">\n\t\t<span class=\"img-thum\">\n\t\t\t<span class=\"img-center\">\n\t\t\t\t<img src=\"https://entertainimg.kbsmedia.co.kr/cms/uploads/CONTENTS_20220812154526_a5a3c299a435f594a4772c92f403797d.jpg\" alt=\"대체 텍스트\">\n\t\t\t</span>\n\t\t</span>\n\t</span></a>\n\t<span class=\"txt\">\n\t\t<span class=\"max-progtit\"><a href=\"https://kstar.kbs.co.kr/list_view.html?idx=223686\">[독립영화관] '습도 다소 높음' 고봉수 스타일을 아시나요 (고봉수 감독,2021)</a></span>\n\t\t<em class=\"prog\"><a href=\"https://kstar.kbs.co.kr/list.html?program_title=%EB%8F%85%EB%A6%BD%EC%98%81%ED%99%94%EA%B4%80\">독립영화관</a></em>\n\t</span>","link":"https://kstar.kbs.co.kr/list_view.html?idx=223686","retrieved":1660287730272,"image":"https://entertainimg.kbsmedia.co.kr/cms/uploads/CONTENTS_20220812154526_a5a3c299a435f594a4772c92f403797d.jpg"},{"title":"2022 카타르월드컵, KBS와 함께 \"구자철 조원희,해설 투톱\"","contents":"<a href=\"https://kstar.kbs.co.kr/list_view.html?idx=223572\">\t<span class=\"img-box ww\">\n\t\t<span class=\"img-thum\">\n\t\t\t<span class=\"img-center\">\n\t\t\t\t<img src=\"https://entertainimg.kbsmedia.co.kr/cms/uploads/CONTENTS_20220812122555_60861e37f2dd06eaf531bdb120ecd05d_1.jpg\" alt=\"대체 텍스트\">\n\t\t\t</span>\n\t\t</span>\n\t</span></a>\n\t<span class=\"txt\">\n\t\t<span class=\"max-progtit\"><a href=\"https://kstar.kbs.co.kr/list_view.html?idx=223572\">2022 카타르월드컵, KBS와 함께 \"구자철 조원희,해설 투톱\"</a></span>\n\t</span>","link":"https://kstar.kbs.co.kr/list_view.html?idx=223572","retrieved":1660287730286,"image":"https://entertainimg.kbsmedia.co.kr/cms/uploads/CONTENTS_20220812122555_60861e37f2dd06eaf531bdb120ecd05d_1.jpg"},{"title":"예능돌 이기광의 귀환...'홍김동전' 남다른 예능감 선보여","contents":"<a href=\"https://kstar.kbs.co.kr/list_view.html?idx=223540\">\t<span class=\"img-box hh\">\n\t\t<span class=\"img-thum\">\n\t\t\t<span class=\"img-center\">\n\t\t\t\t<img src=\"https://entertainimg.kbsmedia.co.kr/cms/uploads/CONTENTS_20220812085135_b4210673aa63ae4fb63552a771be48c3.jpg\" alt=\"대체 텍스트\">\n\t\t\t</span>\n\t\t</span>\n\t</span></a>\n\t<span class=\"txt\">\n\t\t<span class=\"max-progtit\"><a href=\"https://kstar.kbs.co.kr/list_view.html?idx=223540\">예능돌 이기광의 귀환...'홍김동전' 남다른 예능감 선보여</a></span>\n\t\t<em class=\"prog\"><a href=\"https://kstar.kbs.co.kr/list.html?program_title=%ED%99%8D%EA%B9%80%EB%8F%99%EC%A0%84\">홍김동전</a></em>\n\t</span>","link":"https://kstar.kbs.co.kr/list_view.html?idx=223540","retrieved":1660273088471,"image":"https://entertainimg.kbsmedia.co.kr/cms/uploads/CONTENTS_20220812085135_b4210673aa63ae4fb63552a771be48c3.jpg"},{"title":"류수영 셰프 최신 역작 '로제 부대찌개'","contents":"<a href=\"https://kstar.kbs.co.kr/list_view.html?idx=223506\">\t<span class=\"img-box ww\">\n\t\t<span class=\"img-thum\">\n\t\t\t<span class=\"img-center\">\n\t\t\t\t<img src=\"https://entertainimg.kbsmedia.co.kr/cms/uploads/CONTENTS_20220812080656_d455a91f37ab6763b420bc0da2387617.jpg\" alt=\"대체 텍스트\">\n\t\t\t</span>\n\t\t</span>\n\t</span></a>\n\t<span class=\"txt\">\n\t\t<span class=\"max-progtit\"><a href=\"https://kstar.kbs.co.kr/list_view.html?idx=223506\">류수영 셰프 최신 역작 '로제 부대찌개'</a></span>\n\t\t<em class=\"prog\"><a href=\"https://kstar.kbs.co.kr/list.html?program_title=%EC%8B%A0%EC%83%81%20%EC%B6%9C%EC%8B%9C%20%ED%8E%B8%EC%8A%A4%ED%86%A0%EB%9E%91\">신상 출시 편스토랑</a></em>\n\t</span>","link":"https://kstar.kbs.co.kr/list_view.html?idx=223506","retrieved":1660273088472,"image":"https://entertainimg.kbsmedia.co.kr/cms/uploads/CONTENTS_20220812080656_d455a91f37ab6763b420bc0da2387617.jpg"},{"title":"'다큐온' 우리는 섬으로 간다 -  활도(活島) 프로젝트","contents":"<a href=\"https://kstar.kbs.co.kr/list_view.html?idx=223495\">\t<span class=\"img-box hh\">\n\t\t<span class=\"img-thum\">\n\t\t\t<span class=\"img-center\">\n\t\t\t\t<img src=\"https://entertainimg.kbsmedia.co.kr/cms/uploads/CONTENTS_20220812075752_4294f59d48f607b70c3f544a66cabf16_1.png\" alt=\"대체 텍스트\">\n\t\t\t</span>\n\t\t</span>\n\t</span></a>\n\t<span class=\"txt\">\n\t\t<span class=\"max-progtit\"><a href=\"https://kstar.kbs.co.kr/list_view.html?idx=223495\">'다큐온' 우리는 섬으로 간다 -  활도(活島) 프로젝트</a></span>\n\t\t<em class=\"prog\"><a href=\"https://kstar.kbs.co.kr/list.html?program_title=%EB%8B%A4%ED%81%90%20%EC%98%A8\">다큐 온</a></em>\n\t</span>","link":"https://kstar.kbs.co.kr/list_view.html?idx=223495","retrieved":1660273088472,"image":"https://entertainimg.kbsmedia.co.kr/cms/uploads/CONTENTS_20220812075752_4294f59d48f607b70c3f544a66cabf16_1.png"},{"title":"[연중 라이브] 우영우 촬영장의 비하인드 대 공개~!","contents":"<a href=\"https://kstar.kbs.co.kr/list_view.html?idx=223482\">\t<span class=\"img-box ww\">\n\t\t<span class=\"img-thum\">\n\t\t\t<span class=\"img-center\">\n\t\t\t\t<img src=\"https://entertainimg.kbsmedia.co.kr/cms/uploads/CONTENTS_20220812025700_ab09b906d755c2fe8db9b6bb7e434347.jpg\" alt=\"대체 텍스트\">\n\t\t\t</span>\n\t\t</span>\n\t</span></a>\n\t<span class=\"txt\">\n\t\t<span class=\"max-progtit\"><a href=\"https://kstar.kbs.co.kr/list_view.html?idx=223482\">[연중 라이브] 우영우 촬영장의 비하인드 대 공개~!</a></span>\n\t\t<em class=\"prog\"><a href=\"https://kstar.kbs.co.kr/list.html?program_title=%EC%97%B0%EC%A4%91%20%EB%9D%BC%EC%9D%B4%EB%B8%8C\">연중 라이브</a></em>\n\t</span>","link":"https://kstar.kbs.co.kr/list_view.html?idx=223482","retrieved":1660251805158,"image":"https://entertainimg.kbsmedia.co.kr/cms/uploads/CONTENTS_20220812025700_ab09b906d755c2fe8db9b6bb7e434347.jpg"}]}