{"title":"KBS연예 ─ TVs","url":"https://kstar.kbs.co.kr/list.html?cate=TV","favicon":"https://kstar.kbs.co.kr/favicon.ico","elements":[{"title":"[연인 14회] 남궁민, 목숨 걸고 안은진 구했다!","contents":"<a href=\"https://kstar.kbs.co.kr/list_view.html?idx=285294\">\t<span class=\"img-box ww\">\n\t\t<span class=\"img-thum\">\n\t\t\t<span class=\"img-center\">\n\t\t\t\t<img src=\"https://entertainimg.kbsmedia.co.kr/cms/uploads/CONTENTS_20231022074013_5e5e1d021dc3b8bea60fcab3d1b61343.jpg\" alt=\"대체 텍스트\">\n\t\t\t</span>\n\t\t</span>\n\t</span></a>\n\t<span class=\"txt\">\n\t\t<span class=\"max-progtit\"><a href=\"https://kstar.kbs.co.kr/list_view.html?idx=285294\">[연인 14회] 남궁민, 목숨 걸고 안은진 구했다! </a></span>\n\t</span>","link":"https://kstar.kbs.co.kr/list_view.html?idx=285294","retrieved":1697929315154,"image":"https://entertainimg.kbsmedia.co.kr/cms/uploads/CONTENTS_20231022074013_5e5e1d021dc3b8bea60fcab3d1b61343.jpg"},{"title":"[연인] 애틋한 남궁민과 차가운 안은진.. 오늘 100분 편성","contents":"<a href=\"https://kstar.kbs.co.kr/list_view.html?idx=285214\">\t<span class=\"img-box hh\">\n\t\t<span class=\"img-thum\">\n\t\t\t<span class=\"img-center\">\n\t\t\t\t<img src=\"https://entertainimg.kbsmedia.co.kr/cms/uploads/CONTENTS_20231021194240_161722e10c9b4a1b2342d60d0c1117a1.jpg\" alt=\"대체 텍스트\">\n\t\t\t</span>\n\t\t</span>\n\t</span></a>\n\t<span class=\"txt\">\n\t\t<span class=\"max-progtit\"><a href=\"https://kstar.kbs.co.kr/list_view.html?idx=285214\">[연인] 애틋한 남궁민과 차가운 안은진.. 오늘 100분 편성 </a></span>\n\t</span>","link":"https://kstar.kbs.co.kr/list_view.html?idx=285214","retrieved":1697886118784,"image":"https://entertainimg.kbsmedia.co.kr/cms/uploads/CONTENTS_20231021194240_161722e10c9b4a1b2342d60d0c1117a1.jpg"},{"title":"[놀라운 토요일] 거침없는 '제시' - 상큼한 '츄'","contents":"<a href=\"https://kstar.kbs.co.kr/list_view.html?idx=285191\">\t<span class=\"img-box hh\">\n\t\t<span class=\"img-thum\">\n\t\t\t<span class=\"img-center\">\n\t\t\t\t<img src=\"https://entertainimg.kbsmedia.co.kr/cms/uploads/CONTENTS_20231021190102_0861817d7360244ab36815e7a8f24300.jpg\" alt=\"대체 텍스트\">\n\t\t\t</span>\n\t\t</span>\n\t</span></a>\n\t<span class=\"txt\">\n\t\t<span class=\"max-progtit\"><a href=\"https://kstar.kbs.co.kr/list_view.html?idx=285191\">[놀라운 토요일] 거침없는 '제시' - 상큼한 '츄' </a></span>\n\t</span>","link":"https://kstar.kbs.co.kr/list_view.html?idx=285191","retrieved":1697882498782,"image":"https://entertainimg.kbsmedia.co.kr/cms/uploads/CONTENTS_20231021190102_0861817d7360244ab36815e7a8f24300.jpg"},{"title":"'연인 파트2' 이청아의 정체,  황녀 ‘각화’","contents":"<a href=\"https://kstar.kbs.co.kr/list_view.html?idx=285149\">\t<span class=\"img-box ww\">\n\t\t<span class=\"img-thum\">\n\t\t\t<span class=\"img-center\">\n\t\t\t\t<img src=\"https://entertainimg.kbsmedia.co.kr/cms/uploads/CONTENTS_20231021090547_09be1b1485e62ba29cfefce6aa2c6163.jpg\" alt=\"대체 텍스트\">\n\t\t\t</span>\n\t\t</span>\n\t</span></a>\n\t<span class=\"txt\">\n\t\t<span class=\"max-progtit\"><a href=\"https://kstar.kbs.co.kr/list_view.html?idx=285149\">'연인 파트2' 이청아의 정체,  황녀 ‘각화’</a></span>\n\t</span>","link":"https://kstar.kbs.co.kr/list_view.html?idx=285149","retrieved":1697847925404,"image":"https://entertainimg.kbsmedia.co.kr/cms/uploads/CONTENTS_20231021090547_09be1b1485e62ba29cfefce6aa2c6163.jpg"},{"title":"'무인도의 디바' 박은빈-김효진, 반짝이는 두 디바의 만남","contents":"<a href=\"https://kstar.kbs.co.kr/list_view.html?idx=284575\">\t<span class=\"img-box hh\">\n\t\t<span class=\"img-thum\">\n\t\t\t<span class=\"img-center\">\n\t\t\t\t<img src=\"https://entertainimg.kbsmedia.co.kr/cms/uploads/CONTENTS_20231017091236_b392317edd9af7dd6487f2c1c86ad075.jpg\" alt=\"대체 텍스트\">\n\t\t\t</span>\n\t\t</span>\n\t</span></a>\n\t<span class=\"txt\">\n\t\t<span class=\"max-progtit\"><a href=\"https://kstar.kbs.co.kr/list_view.html?idx=284575\">'무인도의 디바' 박은빈-김효진, 반짝이는 두 디바의 만남</a></span>\n\t</span>","link":"https://kstar.kbs.co.kr/list_view.html?idx=284575","retrieved":1697745703372,"image":"https://entertainimg.kbsmedia.co.kr/cms/uploads/CONTENTS_20231017091236_b392317edd9af7dd6487f2c1c86ad075.jpg"},{"title":"‘국민사형투표’ 임지연은 수사 중..  교복 차림으로 권석주 행방 찾기","contents":"<a href=\"https://kstar.kbs.co.kr/list_view.html?idx=284978\">\t<span class=\"img-box hh\">\n\t\t<span class=\"img-thum\">\n\t\t\t<span class=\"img-center\">\n\t\t\t\t<img src=\"https://entertainimg.kbsmedia.co.kr/cms/uploads/CONTENTS_20231019111441_6c4c100d713e914577a68abc56459686.jpg\" alt=\"대체 텍스트\">\n\t\t\t</span>\n\t\t</span>\n\t</span></a>\n\t<span class=\"txt\">\n\t\t<span class=\"max-progtit\"><a href=\"https://kstar.kbs.co.kr/list_view.html?idx=284978\">‘국민사형투표’ 임지연은 수사 중..  교복 차림으로 권석주 행방 찾기</a></span>\n\t</span>","link":"https://kstar.kbs.co.kr/list_view.html?idx=284978","retrieved":1697681719226,"image":"https://entertainimg.kbsmedia.co.kr/cms/uploads/CONTENTS_20231019111441_6c4c100d713e914577a68abc56459686.jpg"},{"title":"[어서와한국은처음이지] 브라질 형제들, \"어서와, 평양냉면은 처음이지?\"","contents":"<a href=\"https://kstar.kbs.co.kr/list_view.html?idx=284966\">\t<span class=\"img-box ww\">\n\t\t<span class=\"img-thum\">\n\t\t\t<span class=\"img-center\">\n\t\t\t\t<img src=\"https://entertainimg.kbsmedia.co.kr/cms/uploads/CONTENTS_20231019105819_dfcdd3931376501f0235e15b0467c11c.jpg\" alt=\"대체 텍스트\">\n\t\t\t</span>\n\t\t</span>\n\t</span></a>\n\t<span class=\"txt\">\n\t\t<span class=\"max-progtit\"><a href=\"https://kstar.kbs.co.kr/list_view.html?idx=284966\">[어서와한국은처음이지] 브라질 형제들, \"어서와, 평양냉면은 처음이지?\"</a></span>\n\t</span>","link":"https://kstar.kbs.co.kr/list_view.html?idx=284966","retrieved":1697681719226,"image":"https://entertainimg.kbsmedia.co.kr/cms/uploads/CONTENTS_20231019105819_dfcdd3931376501f0235e15b0467c11c.jpg"},{"title":"[라디오스타] 장항준-송은이 입담 대결.. \"'오픈 더 도어' 시나리오, 네가 안 썼지?\"","contents":"<a href=\"https://kstar.kbs.co.kr/list_view.html?idx=284920\">\t<span class=\"img-box hh\">\n\t\t<span class=\"img-thum\">\n\t\t\t<span class=\"img-center\">\n\t\t\t\t<img src=\"https://entertainimg.kbsmedia.co.kr/cms/uploads/CONTENTS_20231019093745_a7f87cd20ce46b63c99371bccd4d08f9.png\" alt=\"대체 텍스트\">\n\t\t\t</span>\n\t\t</span>\n\t</span></a>\n\t<span class=\"txt\">\n\t\t<span class=\"max-progtit\"><a href=\"https://kstar.kbs.co.kr/list_view.html?idx=284920\">[라디오스타] 장항준-송은이 입담 대결.. \"'오픈 더 도어' 시나리오, 네가 안 썼지?\"</a></span>\n\t</span>","link":"https://kstar.kbs.co.kr/list_view.html?idx=284920","retrieved":1697679677628,"image":"https://entertainimg.kbsmedia.co.kr/cms/uploads/CONTENTS_20231019093745_a7f87cd20ce46b63c99371bccd4d08f9.png"},{"title":"[유퀴즈온더블럭]  ‘쨍하고 해 뜰 날’ 특집... \"태양처럼 빛나는 사람들\"","contents":"<a href=\"https://kstar.kbs.co.kr/list_view.html?idx=284731\">\t<span class=\"img-box hh\">\n\t\t<span class=\"img-thum\">\n\t\t\t<span class=\"img-center\">\n\t\t\t\t<img src=\"https://entertainimg.kbsmedia.co.kr/cms/uploads/CONTENTS_20231018105601_29d525822b0d37ed7456efc61f17da95.jpg\" alt=\"대체 텍스트\">\n\t\t\t</span>\n\t\t</span>\n\t</span></a>\n\t<span class=\"txt\">\n\t\t<span class=\"max-progtit\"><a href=\"https://kstar.kbs.co.kr/list_view.html?idx=284731\">[유퀴즈온더블럭]  ‘쨍하고 해 뜰 날’ 특집... \"태양처럼 빛나는 사람들\"</a></span>\n\t</span>","link":"https://kstar.kbs.co.kr/list_view.html?idx=284731","retrieved":1697595334621,"image":"https://entertainimg.kbsmedia.co.kr/cms/uploads/CONTENTS_20231018105601_29d525822b0d37ed7456efc61f17da95.jpg"},{"title":"‘연인’ 남궁민-안은진, \"슬픈 운명, 애절한 멜로\"","contents":"<a href=\"https://kstar.kbs.co.kr/list_view.html?idx=284679\">\t<span class=\"img-box hh\">\n\t\t<span class=\"img-thum\">\n\t\t\t<span class=\"img-center\">\n\t\t\t\t<img src=\"https://entertainimg.kbsmedia.co.kr/cms/uploads/CONTENTS_20231018084812_b440c827d854f512dcf8ac4694cf519c_1.jpg\" alt=\"대체 텍스트\">\n\t\t\t</span>\n\t\t</span>\n\t</span></a>\n\t<span class=\"txt\">\n\t\t<span class=\"max-progtit\"><a href=\"https://kstar.kbs.co.kr/list_view.html?idx=284679\">‘연인’ 남궁민-안은진, \"슬픈 운명, 애절한 멜로\"</a></span>\n\t</span>","link":"https://kstar.kbs.co.kr/list_view.html?idx=284679","retrieved":1697588757101,"image":"https://entertainimg.kbsmedia.co.kr/cms/uploads/CONTENTS_20231018084812_b440c827d854f512dcf8ac4694cf519c_1.jpg"},{"title":"'무인도의 디바' 채종협-차학연-김주헌, \"박은빈-김효진을 응원해!\"","contents":"<a href=\"https://kstar.kbs.co.kr/list_view.html?idx=284570\">\t<span class=\"img-box hh\">\n\t\t<span class=\"img-thum\">\n\t\t\t<span class=\"img-center\">\n\t\t\t\t<img src=\"https://entertainimg.kbsmedia.co.kr/cms/uploads/CONTENTS_20231017090802_78d1dc13fd3625b8129bb560cd9f5eb7.jpg\" alt=\"대체 텍스트\">\n\t\t\t</span>\n\t\t</span>\n\t</span></a>\n\t<span class=\"txt\">\n\t\t<span class=\"max-progtit\"><a href=\"https://kstar.kbs.co.kr/list_view.html?idx=284570\">'무인도의 디바' 채종협-차학연-김주헌, \"박은빈-김효진을 응원해!\"</a></span>\n\t</span>","link":"https://kstar.kbs.co.kr/list_view.html?idx=284570","retrieved":1697502360639,"image":"https://entertainimg.kbsmedia.co.kr/cms/uploads/CONTENTS_20231017090802_78d1dc13fd3625b8129bb560cd9f5eb7.jpg"},{"title":"[반짝이는워터멜론 7회] 려운-최현욱-설인아-신은수, 뒤틀린 시공간 속 네 청춘","contents":"<a href=\"https://kstar.kbs.co.kr/list_view.html?idx=284530\">\t<span class=\"img-box ww\">\n\t\t<span class=\"img-thum\">\n\t\t\t<span class=\"img-center\">\n\t\t\t\t<img src=\"https://entertainimg.kbsmedia.co.kr/cms/uploads/CONTENTS_20231017081853_f7d8ff3b22abfd7a03c711652c43ed2f.jpg\" alt=\"대체 텍스트\">\n\t\t\t</span>\n\t\t</span>\n\t</span></a>\n\t<span class=\"txt\">\n\t\t<span class=\"max-progtit\"><a href=\"https://kstar.kbs.co.kr/list_view.html?idx=284530\">[반짝이는워터멜론 7회] 려운-최현욱-설인아-신은수, 뒤틀린 시공간 속 네 청춘</a></span>\n\t</span>","link":"https://kstar.kbs.co.kr/list_view.html?idx=284530","retrieved":1697502360643,"image":"https://entertainimg.kbsmedia.co.kr/cms/uploads/CONTENTS_20231017081853_f7d8ff3b22abfd7a03c711652c43ed2f.jpg"},{"title":"[반짝이는 워터멜론] 신은수 애틋한 고백.. \"나를 발견해줘서 고마워\"","contents":"<a href=\"https://kstar.kbs.co.kr/list_view.html?idx=284384\">\t<span class=\"img-box hh\">\n\t\t<span class=\"img-thum\">\n\t\t\t<span class=\"img-center\">\n\t\t\t\t<img src=\"https://entertainimg.kbsmedia.co.kr/cms/uploads/CONTENTS_20231016072319_2f3decd1e58ad7f6ce5a3dd23b236d78_1.jpg\" alt=\"대체 텍스트\">\n\t\t\t</span>\n\t\t</span>\n\t</span></a>\n\t<span class=\"txt\">\n\t\t<span class=\"max-progtit\"><a href=\"https://kstar.kbs.co.kr/list_view.html?idx=284384\">[반짝이는 워터멜론] 신은수 애틋한 고백.. \"나를 발견해줘서 고마워\"</a></span>\n\t</span>","link":"https://kstar.kbs.co.kr/list_view.html?idx=284384","retrieved":1697410917575,"image":"https://entertainimg.kbsmedia.co.kr/cms/uploads/CONTENTS_20231016072319_2f3decd1e58ad7f6ce5a3dd23b236d78_1.jpg"},{"title":"[연인] 안은진, 위기에 빛나다... \"처절할수록 강인해지는 유길채\"","contents":"<a href=\"https://kstar.kbs.co.kr/list_view.html?idx=284378\">\t<span class=\"img-box ww\">\n\t\t<span class=\"img-thum\">\n\t\t\t<span class=\"img-center\">\n\t\t\t\t<img src=\"https://entertainimg.kbsmedia.co.kr/cms/uploads/CONTENTS_20231016071844_b9fe8851c484ab678013abdd94da19f3.jpg\" alt=\"대체 텍스트\">\n\t\t\t</span>\n\t\t</span>\n\t</span></a>\n\t<span class=\"txt\">\n\t\t<span class=\"max-progtit\"><a href=\"https://kstar.kbs.co.kr/list_view.html?idx=284378\">[연인] 안은진, 위기에 빛나다... \"처절할수록 강인해지는 유길채\"</a></span>\n\t</span>","link":"https://kstar.kbs.co.kr/list_view.html?idx=284378","retrieved":1697410917575,"image":"https://entertainimg.kbsmedia.co.kr/cms/uploads/CONTENTS_20231016071844_b9fe8851c484ab678013abdd94da19f3.jpg"},{"title":"MBC에브리원 ‘위대한 가이드’, 현지인 착붙 여행 리얼리티 프로그램... \"알레르토와 베네치아!\"","contents":"<a href=\"https://kstar.kbs.co.kr/list_view.html?idx=284284\">\t<span class=\"img-box ww\">\n\t\t<span class=\"img-thum\">\n\t\t\t<span class=\"img-center\">\n\t\t\t\t<img src=\"https://entertainimg.kbsmedia.co.kr/cms/uploads/CONTENTS_20231015161323_0974f4b3091706a21a350b3c72cd7396.jpg\" alt=\"대체 텍스트\">\n\t\t\t</span>\n\t\t</span>\n\t</span></a>\n\t<span class=\"txt\">\n\t\t<span class=\"max-progtit\"><a href=\"https://kstar.kbs.co.kr/list_view.html?idx=284284\">MBC에브리원 ‘위대한 가이드’, 현지인 착붙 여행 리얼리티 프로그램... \"알레르토와 베네치아!\"</a></span>\n\t</span>","link":"https://kstar.kbs.co.kr/list_view.html?idx=284284","retrieved":1697407319902,"image":"https://entertainimg.kbsmedia.co.kr/cms/uploads/CONTENTS_20231015161323_0974f4b3091706a21a350b3c72cd7396.jpg"},{"title":"[힘쎈여자 강남순] ‘괴력소녀’ 이유미 X ‘열혈형사’ 옹성우, ‘힘쎈 콤비’ 결성","contents":"<a href=\"https://kstar.kbs.co.kr/list_view.html?idx=284272\">\t<span class=\"img-box hh\">\n\t\t<span class=\"img-thum\">\n\t\t\t<span class=\"img-center\">\n\t\t\t\t<img src=\"https://entertainimg.kbsmedia.co.kr/cms/uploads/CONTENTS_20231015160457_212cae065431ba7538b2ebfb4e59e4da.png\" alt=\"대체 텍스트\">\n\t\t\t</span>\n\t\t</span>\n\t</span></a>\n\t<span class=\"txt\">\n\t\t<span class=\"max-progtit\"><a href=\"https://kstar.kbs.co.kr/list_view.html?idx=284272\">[힘쎈여자 강남순] ‘괴력소녀’ 이유미 X ‘열혈형사’ 옹성우, ‘힘쎈 콤비’ 결성</a></span>\n\t</span>","link":"https://kstar.kbs.co.kr/list_view.html?idx=284272","retrieved":1697356926790,"image":"https://entertainimg.kbsmedia.co.kr/cms/uploads/CONTENTS_20231015160457_212cae065431ba7538b2ebfb4e59e4da.png"},{"title":"'놀라운 토요일' 임영웅, 스페셜 단독 게스트 출격","contents":"<a href=\"https://kstar.kbs.co.kr/list_view.html?idx=284217\">\t<span class=\"img-box hh\">\n\t\t<span class=\"img-thum\">\n\t\t\t<span class=\"img-center\">\n\t\t\t\t<img src=\"https://entertainimg.kbsmedia.co.kr/cms/uploads/CONTENTS_20231014123742_35c2c3365b53eef01250dbdfdff296e1_1.jpg\" alt=\"대체 텍스트\">\n\t\t\t</span>\n\t\t</span>\n\t</span></a>\n\t<span class=\"txt\">\n\t\t<span class=\"max-progtit\"><a href=\"https://kstar.kbs.co.kr/list_view.html?idx=284217\">'놀라운 토요일' 임영웅, 스페셜 단독 게스트 출격</a></span>\n\t</span>","link":"https://kstar.kbs.co.kr/list_view.html?idx=284217","retrieved":1697256167000,"image":"https://entertainimg.kbsmedia.co.kr/cms/uploads/CONTENTS_20231014123742_35c2c3365b53eef01250dbdfdff296e1_1.jpg"},{"title":"‘악인전기’ 오늘 첫 방송.. 신하균x김영광x신재하, \"범죄 느와르\"","contents":"<a href=\"https://kstar.kbs.co.kr/list_view.html?idx=284205\">\t<span class=\"img-box hh\">\n\t\t<span class=\"img-thum\">\n\t\t\t<span class=\"img-center\">\n\t\t\t\t<img src=\"https://entertainimg.kbsmedia.co.kr/cms/uploads/CONTENTS_20231014084432_0d3280e9594333bee0153a915a68483f.jpg\" alt=\"대체 텍스트\">\n\t\t\t</span>\n\t\t</span>\n\t</span></a>\n\t<span class=\"txt\">\n\t\t<span class=\"max-progtit\"><a href=\"https://kstar.kbs.co.kr/list_view.html?idx=284205\">‘악인전기’ 오늘 첫 방송.. 신하균x김영광x신재하, \"범죄 느와르\"</a></span>\n\t</span>","link":"https://kstar.kbs.co.kr/list_view.html?idx=284205","retrieved":1697243068029,"image":"https://entertainimg.kbsmedia.co.kr/cms/uploads/CONTENTS_20231014084432_0d3280e9594333bee0153a915a68483f.jpg"},{"title":"[힘쎈여자 강남순 3회] 도봉순 커플 박보영-박형식, 3회 특별출연","contents":"<a href=\"https://kstar.kbs.co.kr/list_view.html?idx=284098\">\t<span class=\"img-box hh\">\n\t\t<span class=\"img-thum\">\n\t\t\t<span class=\"img-center\">\n\t\t\t\t<img src=\"https://entertainimg.kbsmedia.co.kr/cms/uploads/CONTENTS_20231013142736_8bb3166cc2d8525fd6be0141eedf942c_1.png\" alt=\"대체 텍스트\">\n\t\t\t</span>\n\t\t</span>\n\t</span></a>\n\t<span class=\"txt\">\n\t\t<span class=\"max-progtit\"><a href=\"https://kstar.kbs.co.kr/list_view.html?idx=284098\">[힘쎈여자 강남순 3회] 도봉순 커플 박보영-박형식, 3회 특별출연</a></span>\n\t</span>","link":"https://kstar.kbs.co.kr/list_view.html?idx=284098","retrieved":1697238091471,"image":"https://entertainimg.kbsmedia.co.kr/cms/uploads/CONTENTS_20231013142736_8bb3166cc2d8525fd6be0141eedf942c_1.png"},{"title":"[종영소감] 조보아 ‘이 연애는 불가항력’.. \"홍조·앵초 사랑해주셔서 감사\"","contents":"<a href=\"https://kstar.kbs.co.kr/list_view.html?idx=284085\">\t<span class=\"img-box hh\">\n\t\t<span class=\"img-thum\">\n\t\t\t<span class=\"img-center\">\n\t\t\t\t<img src=\"https://entertainimg.kbsmedia.co.kr/cms/uploads/CONTENTS_20231013141755_9ca8cd6b6831b8c3c4d218f7642f879c.png\" alt=\"대체 텍스트\">\n\t\t\t</span>\n\t\t</span>\n\t</span></a>\n\t<span class=\"txt\">\n\t\t<span class=\"max-progtit\"><a href=\"https://kstar.kbs.co.kr/list_view.html?idx=284085\">[종영소감] 조보아 ‘이 연애는 불가항력’.. \"홍조·앵초 사랑해주셔서 감사\"</a></span>\n\t</span>","link":"https://kstar.kbs.co.kr/list_view.html?idx=284085","retrieved":1697176910158,"image":"https://entertainimg.kbsmedia.co.kr/cms/uploads/CONTENTS_20231013141755_9ca8cd6b6831b8c3c4d218f7642f879c.png"}]}