{"title":"KBS연예 ─ 영화","url":"https://kstar.kbs.co.kr/list.html?cate=MV","favicon":"https://kstar.kbs.co.kr/favicon.ico","elements":[{"title":"CJ ENM, 베트남 합작영화 '마이' 현지 흥행 돌풍","contents":"<a href=\"https://kstar.kbs.co.kr/list_view.html?idx=303381\">\t<span class=\"img-box hh\">\n\t\t<span class=\"img-thum\">\n\t\t\t<span class=\"img-center\">\n\t\t\t\t<img src=\"https://entertainimg.kbsmedia.co.kr/cms/uploads/CONTENTS_20240216105115_5cbf795ca861cb304c3bbb281b2a47f1_1.jpg\" alt=\"대체 텍스트\">\n\t\t\t</span>\n\t\t</span>\n\t</span></a>\n\t<span class=\"txt\">\n\t\t<span class=\"max-progtit\"><a href=\"https://kstar.kbs.co.kr/list_view.html?idx=303381\">CJ ENM, 베트남 합작영화 '마이' 현지 흥행 돌풍</a></span>\n\t</span>","link":"https://kstar.kbs.co.kr/list_view.html?idx=303381","retrieved":1708049583052,"image":"https://entertainimg.kbsmedia.co.kr/cms/uploads/CONTENTS_20240216105115_5cbf795ca861cb304c3bbb281b2a47f1_1.jpg"},{"title":"[인터뷰] 이권 감독 \"재밌었나요?\"  (디즈니플러스 ‘킬러들의 쇼핑몰’)","contents":"<a href=\"https://kstar.kbs.co.kr/list_view.html?idx=303373\">\t<span class=\"img-box hh\">\n\t\t<span class=\"img-thum\">\n\t\t\t<span class=\"img-center\">\n\t\t\t\t<img src=\"https://entertainimg.kbsmedia.co.kr/cms/uploads/CONTENTS_20240216093558_67a7c037dab6eb75f7ae7b4864f67313.png\" alt=\"대체 텍스트\">\n\t\t\t</span>\n\t\t</span>\n\t</span></a>\n\t<span class=\"txt\">\n\t\t<span class=\"max-progtit\"><a href=\"https://kstar.kbs.co.kr/list_view.html?idx=303373\">[인터뷰] 이권 감독 \"재밌었나요?\"  (디즈니플러스 ‘킬러들의 쇼핑몰’)</a></span>\n\t</span>","link":"https://kstar.kbs.co.kr/list_view.html?idx=303373","retrieved":1708047523461,"image":"https://entertainimg.kbsmedia.co.kr/cms/uploads/CONTENTS_20240216093558_67a7c037dab6eb75f7ae7b4864f67313.png"},{"title":"송혜교의 새 영화 '검은 수녀들'.. \"전여빈, 이진욱, 허준호, 문우진 합류\"","contents":"<a href=\"https://kstar.kbs.co.kr/list_view.html?idx=303339\">\t<span class=\"img-box hh\">\n\t\t<span class=\"img-thum\">\n\t\t\t<span class=\"img-center\">\n\t\t\t\t<img src=\"https://entertainimg.kbsmedia.co.kr/cms/uploads/CONTENTS_20240216081312_af79c8d994c9d56729b2fbe398ff8431.png\" alt=\"대체 텍스트\">\n\t\t\t</span>\n\t\t</span>\n\t</span></a>\n\t<span class=\"txt\">\n\t\t<span class=\"max-progtit\"><a href=\"https://kstar.kbs.co.kr/list_view.html?idx=303339\">송혜교의 새 영화 '검은 수녀들'.. \"전여빈, 이진욱, 허준호, 문우진 합류\"</a></span>\n\t</span>","link":"https://kstar.kbs.co.kr/list_view.html?idx=303339","retrieved":1708043138600,"image":"https://entertainimg.kbsmedia.co.kr/cms/uploads/CONTENTS_20240216081312_af79c8d994c9d56729b2fbe398ff8431.png"},{"title":"티빙 ‘크라임씬 리턴즈’ 주현영, \"과몰입 유발, 맞춤형 인재\"","contents":"<a href=\"https://kstar.kbs.co.kr/list_view.html?idx=303326\">\t<span class=\"img-box hh\">\n\t\t<span class=\"img-thum\">\n\t\t\t<span class=\"img-center\">\n\t\t\t\t<img src=\"https://entertainimg.kbsmedia.co.kr/cms/uploads/CONTENTS_20240216075710_d024373e1a48945fb22fa0242dd9a227.jpg\" alt=\"대체 텍스트\">\n\t\t\t</span>\n\t\t</span>\n\t</span></a>\n\t<span class=\"txt\">\n\t\t<span class=\"max-progtit\"><a href=\"https://kstar.kbs.co.kr/list_view.html?idx=303326\">티빙 ‘크라임씬 리턴즈’ 주현영, \"과몰입 유발, 맞춤형 인재\"</a></span>\n\t</span>","link":"https://kstar.kbs.co.kr/list_view.html?idx=303326","retrieved":1708038088262,"image":"https://entertainimg.kbsmedia.co.kr/cms/uploads/CONTENTS_20240216075710_d024373e1a48945fb22fa0242dd9a227.jpg"},{"title":"\"유럽은 다르다, 넷플릭스는 다르다\"...  '성+인물: 네덜란드, 독일편'  20일 공개","contents":"<a href=\"https://kstar.kbs.co.kr/list_view.html?idx=303075\">\t<span class=\"img-box ww\">\n\t\t<span class=\"img-thum\">\n\t\t\t<span class=\"img-center\">\n\t\t\t\t<img src=\"https://entertainimg.kbsmedia.co.kr/cms/uploads/CONTENTS_20240214074034_0e793b32beabc10029b32fa15c9327fe.jpg\" alt=\"대체 텍스트\">\n\t\t\t</span>\n\t\t</span>\n\t</span></a>\n\t<span class=\"txt\">\n\t\t<span class=\"max-progtit\"><a href=\"https://kstar.kbs.co.kr/list_view.html?idx=303075\">\"유럽은 다르다, 넷플릭스는 다르다\"...  '성+인물: 네덜란드, 독일편'  20일 공개</a></span>\n\t</span>","link":"https://kstar.kbs.co.kr/list_view.html?idx=303075","retrieved":1708038088263,"image":"https://entertainimg.kbsmedia.co.kr/cms/uploads/CONTENTS_20240214074034_0e793b32beabc10029b32fa15c9327fe.jpg"},{"title":"'그랜드샤이닝호텔' 김재경 파격 변신, 팜므파탈 연쇄살인마 ‘박현주’","contents":"<a href=\"https://kstar.kbs.co.kr/list_view.html?idx=303302\">\t<span class=\"img-box hh\">\n\t\t<span class=\"img-thum\">\n\t\t\t<span class=\"img-center\">\n\t\t\t\t<img src=\"https://entertainimg.kbsmedia.co.kr/cms/uploads/CONTENTS_20240216072937_1e4e51e114c4485fb8ab688cc30b8285.jpg\" alt=\"대체 텍스트\">\n\t\t\t</span>\n\t\t</span>\n\t</span></a>\n\t<span class=\"txt\">\n\t\t<span class=\"max-progtit\"><a href=\"https://kstar.kbs.co.kr/list_view.html?idx=303302\">'그랜드샤이닝호텔' 김재경 파격 변신, 팜므파탈 연쇄살인마 ‘박현주’</a></span>\n\t</span>","link":"https://kstar.kbs.co.kr/list_view.html?idx=303302","retrieved":1708038088265,"image":"https://entertainimg.kbsmedia.co.kr/cms/uploads/CONTENTS_20240216072937_1e4e51e114c4485fb8ab688cc30b8285.jpg"},{"title":"'원 앤 온리' 왕이보의 새 영화 \"무대 위 청춘의 모든 순간\"","contents":"<a href=\"https://kstar.kbs.co.kr/list_view.html?idx=302894\">\t<span class=\"img-box ww\">\n\t\t<span class=\"img-thum\">\n\t\t\t<span class=\"img-center\">\n\t\t\t\t<img src=\"https://entertainimg.kbsmedia.co.kr/cms/uploads/CONTENTS_20240213091636_1a8ab0974a65bc031a8f670c44fbcccf.jpg\" alt=\"대체 텍스트\">\n\t\t\t</span>\n\t\t</span>\n\t</span></a>\n\t<span class=\"txt\">\n\t\t<span class=\"max-progtit\"><a href=\"https://kstar.kbs.co.kr/list_view.html?idx=302894\">'원 앤 온리' 왕이보의 새 영화 \"무대 위 청춘의 모든 순간\"</a></span>\n\t</span>","link":"https://kstar.kbs.co.kr/list_view.html?idx=302894","retrieved":1708030904020,"image":"https://entertainimg.kbsmedia.co.kr/cms/uploads/CONTENTS_20240213091636_1a8ab0974a65bc031a8f670c44fbcccf.jpg"},{"title":"원작자 꼬마비, \"더할 나위 없었다, 살인자ㅇ난감!\"","contents":"<a href=\"https://kstar.kbs.co.kr/list_view.html?idx=303254\">\t<span class=\"img-box hh\">\n\t\t<span class=\"img-thum\">\n\t\t\t<span class=\"img-center\">\n\t\t\t\t<img src=\"https://entertainimg.kbsmedia.co.kr/cms/uploads/CONTENTS_20240215140304_5b2776933cf5f7c7ac140d9511c2cf94.jpg\" alt=\"대체 텍스트\">\n\t\t\t</span>\n\t\t</span>\n\t</span></a>\n\t<span class=\"txt\">\n\t\t<span class=\"max-progtit\"><a href=\"https://kstar.kbs.co.kr/list_view.html?idx=303254\">원작자 꼬마비, \"더할 나위 없었다, 살인자ㅇ난감!\"</a></span>\n\t</span>","link":"https://kstar.kbs.co.kr/list_view.html?idx=303254","retrieved":1707976897678,"image":"https://entertainimg.kbsmedia.co.kr/cms/uploads/CONTENTS_20240215140304_5b2776933cf5f7c7ac140d9511c2cf94.jpg"},{"title":"넷플릭스 영화 '댐즐',  밀리 바비 브라운의  판타지 어드벤처.. \"이건 디즈니 동화가 아니다\"","contents":"<a href=\"https://kstar.kbs.co.kr/list_view.html?idx=303248\">\t<span class=\"img-box ww\">\n\t\t<span class=\"img-thum\">\n\t\t\t<span class=\"img-center\">\n\t\t\t\t<img src=\"https://entertainimg.kbsmedia.co.kr/cms/uploads/CONTENTS_20240215135533_b02451a9040b311fdc94502cacb260a1.jpg\" alt=\"대체 텍스트\">\n\t\t\t</span>\n\t\t</span>\n\t</span></a>\n\t<span class=\"txt\">\n\t\t<span class=\"max-progtit\"><a href=\"https://kstar.kbs.co.kr/list_view.html?idx=303248\">넷플릭스 영화 '댐즐',  밀리 바비 브라운의  판타지 어드벤처.. \"이건 디즈니 동화가 아니다\"</a></span>\n\t</span>","link":"https://kstar.kbs.co.kr/list_view.html?idx=303248","retrieved":1707973288648,"image":"https://entertainimg.kbsmedia.co.kr/cms/uploads/CONTENTS_20240215135533_b02451a9040b311fdc94502cacb260a1.jpg"},{"title":"\"티빙, 월 5500원\" 국내OTT 최초 ‘광고요금제(AVOD)’ 출시","contents":"<a href=\"https://kstar.kbs.co.kr/list_view.html?idx=303242\">\t<span class=\"img-box hh\">\n\t\t<span class=\"img-thum\">\n\t\t\t<span class=\"img-center\">\n\t\t\t\t<img src=\"https://entertainimg.kbsmedia.co.kr/cms/uploads/CONTENTS_20240215092302_e8927518c067bd7fbe8498fa3e715d40.png\" alt=\"대체 텍스트\">\n\t\t\t</span>\n\t\t</span>\n\t</span></a>\n\t<span class=\"txt\">\n\t\t<span class=\"max-progtit\"><a href=\"https://kstar.kbs.co.kr/list_view.html?idx=303242\">\"티빙, 월 5500원\" 국내OTT 최초 ‘광고요금제(AVOD)’ 출시</a></span>\n\t</span>","link":"https://kstar.kbs.co.kr/list_view.html?idx=303242","retrieved":1707956743980,"image":"https://entertainimg.kbsmedia.co.kr/cms/uploads/CONTENTS_20240215092302_e8927518c067bd7fbe8498fa3e715d40.png"},{"title":"'헤일로 시즌2' 3화, 오늘 공개... '관 하, 핼시 박사, 소렌의 길\"","contents":"<a href=\"https://kstar.kbs.co.kr/list_view.html?idx=303196\">\t<span class=\"img-box hh\">\n\t\t<span class=\"img-thum\">\n\t\t\t<span class=\"img-center\">\n\t\t\t\t<img src=\"https://entertainimg.kbsmedia.co.kr/cms/uploads/CONTENTS_20240215083045_284a7a45934d051fd4433520e31b43e2.jpg\" alt=\"대체 텍스트\">\n\t\t\t</span>\n\t\t</span>\n\t</span></a>\n\t<span class=\"txt\">\n\t\t<span class=\"max-progtit\"><a href=\"https://kstar.kbs.co.kr/list_view.html?idx=303196\">'헤일로 시즌2' 3화, 오늘 공개... '관 하, 핼시 박사, 소렌의 길\"</a></span>\n\t</span>","link":"https://kstar.kbs.co.kr/list_view.html?idx=303196","retrieved":1707956743980,"image":"https://entertainimg.kbsmedia.co.kr/cms/uploads/CONTENTS_20240215083045_284a7a45934d051fd4433520e31b43e2.jpg"},{"title":"애플TV+, '발렌타인데이' 스페셜 콘텐츠...   ‘차 차 리얼 스무스’, '플라토닉', '찰리 브라운...'","contents":"<a href=\"https://kstar.kbs.co.kr/list_view.html?idx=303189\">\t<span class=\"img-box hh\">\n\t\t<span class=\"img-thum\">\n\t\t\t<span class=\"img-center\">\n\t\t\t\t<img src=\"https://entertainimg.kbsmedia.co.kr/cms/uploads/CONTENTS_20240215075536_7f461faeaab362a1bf09f7c6b8cffcdb.jpg\" alt=\"대체 텍스트\">\n\t\t\t</span>\n\t\t</span>\n\t</span></a>\n\t<span class=\"txt\">\n\t\t<span class=\"max-progtit\"><a href=\"https://kstar.kbs.co.kr/list_view.html?idx=303189\">애플TV+, '발렌타인데이' 스페셜 콘텐츠...   ‘차 차 리얼 스무스’, '플라토닉', '찰리 브라운...'</a></span>\n\t</span>","link":"https://kstar.kbs.co.kr/list_view.html?idx=303189","retrieved":1707951686338,"image":"https://entertainimg.kbsmedia.co.kr/cms/uploads/CONTENTS_20240215075536_7f461faeaab362a1bf09f7c6b8cffcdb.jpg"},{"title":"\"아름답다, 모든 것이\"  영화 '오키쿠와 세계' 캐릭터 포스터 공개","contents":"<a href=\"https://kstar.kbs.co.kr/list_view.html?idx=303182\">\t<span class=\"img-box hh\">\n\t\t<span class=\"img-thum\">\n\t\t\t<span class=\"img-center\">\n\t\t\t\t<img src=\"https://entertainimg.kbsmedia.co.kr/cms/uploads/CONTENTS_20240215074244_395a065bd494be520ad584af7e8a64e7.jpg\" alt=\"대체 텍스트\">\n\t\t\t</span>\n\t\t</span>\n\t</span></a>\n\t<span class=\"txt\">\n\t\t<span class=\"max-progtit\"><a href=\"https://kstar.kbs.co.kr/list_view.html?idx=303182\">\"아름답다, 모든 것이\"  영화 '오키쿠와 세계' 캐릭터 포스터 공개</a></span>\n\t</span>","link":"https://kstar.kbs.co.kr/list_view.html?idx=303182","retrieved":1707951686340,"image":"https://entertainimg.kbsmedia.co.kr/cms/uploads/CONTENTS_20240215074244_395a065bd494be520ad584af7e8a64e7.jpg"},{"title":"\"청춘의 정우성, 이정재를 본다\"  김성수 감독 <비트>, <서울의 봄> 3월 재개봉","contents":"<a href=\"https://kstar.kbs.co.kr/list_view.html?idx=302811\">\t<span class=\"img-box ww\">\n\t\t<span class=\"img-thum\">\n\t\t\t<span class=\"img-center\">\n\t\t\t\t<img src=\"https://entertainimg.kbsmedia.co.kr/cms/uploads/CONTENTS_20240212204904_e7ac6d7bbf74ae3267397f452e1ec5a8.jpg\" alt=\"대체 텍스트\">\n\t\t\t</span>\n\t\t</span>\n\t</span></a>\n\t<span class=\"txt\">\n\t\t<span class=\"max-progtit\"><a href=\"https://kstar.kbs.co.kr/list_view.html?idx=302811\">\"청춘의 정우성, 이정재를 본다\"  김성수 감독 &lt;비트&gt;, &lt;서울의 봄&gt; 3월 재개봉</a></span>\n\t</span>","link":"https://kstar.kbs.co.kr/list_view.html?idx=302811","retrieved":1707944485570,"image":"https://entertainimg.kbsmedia.co.kr/cms/uploads/CONTENTS_20240212204904_e7ac6d7bbf74ae3267397f452e1ec5a8.jpg"},{"title":"최동훈 감독 '외계+인' 2부, 오늘부터 안방극장 서비스 시작","contents":"<a href=\"https://kstar.kbs.co.kr/list_view.html?idx=303136\">\t<span class=\"img-box ww\">\n\t\t<span class=\"img-thum\">\n\t\t\t<span class=\"img-center\">\n\t\t\t\t<img src=\"https://entertainimg.kbsmedia.co.kr/cms/uploads/CONTENTS_20240214111411_f05323c19e50511276969fa4163998c1.jpg\" alt=\"대체 텍스트\">\n\t\t\t</span>\n\t\t</span>\n\t</span></a>\n\t<span class=\"txt\">\n\t\t<span class=\"max-progtit\"><a href=\"https://kstar.kbs.co.kr/list_view.html?idx=303136\">최동훈 감독 '외계+인' 2부, 오늘부터 안방극장 서비스 시작</a></span>\n\t</span>","link":"https://kstar.kbs.co.kr/list_view.html?idx=303136","retrieved":1707879707184,"image":"https://entertainimg.kbsmedia.co.kr/cms/uploads/CONTENTS_20240214111411_f05323c19e50511276969fa4163998c1.jpg"},{"title":"\"아카데미 후보에 오르다\"  영화 '바튼 아카데미'.. . \"크리스마스 특별수업\"","contents":"<a href=\"https://kstar.kbs.co.kr/list_view.html?idx=302681\">\t<span class=\"img-box hh\">\n\t\t<span class=\"img-thum\">\n\t\t\t<span class=\"img-center\">\n\t\t\t\t<img src=\"https://entertainimg.kbsmedia.co.kr/cms/uploads/CONTENTS_20240212050812_906b887c91829aa9207a4525a2acc520_1.jpg\" alt=\"대체 텍스트\">\n\t\t\t</span>\n\t\t</span>\n\t</span></a>\n\t<span class=\"txt\">\n\t\t<span class=\"max-progtit\"><a href=\"https://kstar.kbs.co.kr/list_view.html?idx=302681\">\"아카데미 후보에 오르다\"  영화 '바튼 아카데미'.. . \"크리스마스 특별수업\"</a></span>\n\t</span>","link":"https://kstar.kbs.co.kr/list_view.html?idx=302681","retrieved":1707865277587,"image":"https://entertainimg.kbsmedia.co.kr/cms/uploads/CONTENTS_20240212050812_906b887c91829aa9207a4525a2acc520_1.jpg"},{"title":"영화 '갓랜드', \"여기는 신의 땅\"... 19세기, 지독하게 아름다운 아이슬란드","contents":"<a href=\"https://kstar.kbs.co.kr/list_view.html?idx=302618\">\t<span class=\"img-box hh\">\n\t\t<span class=\"img-thum\">\n\t\t\t<span class=\"img-center\">\n\t\t\t\t<img src=\"https://entertainimg.kbsmedia.co.kr/cms/uploads/CONTENTS_20240211202647_facdaecb27804d603303ecd500b84403.jpg\" alt=\"대체 텍스트\">\n\t\t\t</span>\n\t\t</span>\n\t</span></a>\n\t<span class=\"txt\">\n\t\t<span class=\"max-progtit\"><a href=\"https://kstar.kbs.co.kr/list_view.html?idx=302618\">영화 '갓랜드', \"여기는 신의 땅\"... 19세기, 지독하게 아름다운 아이슬란드</a></span>\n\t</span>","link":"https://kstar.kbs.co.kr/list_view.html?idx=302618","retrieved":1707858095980,"image":"https://entertainimg.kbsmedia.co.kr/cms/uploads/CONTENTS_20240211202647_facdaecb27804d603303ecd500b84403.jpg"},{"title":"\"묫자리는 함부로 건드리면 안 되는거야!\" 영화 '파묘' 메인 포스터 공개","contents":"<a href=\"https://kstar.kbs.co.kr/list_view.html?idx=302532\">\t<span class=\"img-box hh\">\n\t\t<span class=\"img-thum\">\n\t\t\t<span class=\"img-center\">\n\t\t\t\t<img src=\"https://entertainimg.kbsmedia.co.kr/cms/uploads/CONTENTS_20240210211739_c64e4aa019fd4a0b039b915664e343d5.jpg\" alt=\"대체 텍스트\">\n\t\t\t</span>\n\t\t</span>\n\t</span></a>\n\t<span class=\"txt\">\n\t\t<span class=\"max-progtit\"><a href=\"https://kstar.kbs.co.kr/list_view.html?idx=302532\">\"묫자리는 함부로 건드리면 안 되는거야!\" 영화 '파묘' 메인 포스터 공개</a></span>\n\t</span>","link":"https://kstar.kbs.co.kr/list_view.html?idx=302532","retrieved":1707858095982,"image":"https://entertainimg.kbsmedia.co.kr/cms/uploads/CONTENTS_20240210211739_c64e4aa019fd4a0b039b915664e343d5.jpg"},{"title":"\"우리는  BEST FRIENDS\"  데드풀 3편은 울버린과 함께..  '데드풀과 울버린' 7월 개봉","contents":"<a href=\"https://kstar.kbs.co.kr/list_view.html?idx=302805\">\t<span class=\"img-box hh\">\n\t\t<span class=\"img-thum\">\n\t\t\t<span class=\"img-center\">\n\t\t\t\t<img src=\"https://entertainimg.kbsmedia.co.kr/cms/uploads/CONTENTS_20240212203531_b214820bd481a5c5f8286592ff5eafa4.png\" alt=\"대체 텍스트\">\n\t\t\t</span>\n\t\t</span>\n\t</span></a>\n\t<span class=\"txt\">\n\t\t<span class=\"max-progtit\"><a href=\"https://kstar.kbs.co.kr/list_view.html?idx=302805\"> \"우리는  BEST FRIENDS\"  데드풀 3편은 울버린과 함께..  '데드풀과 울버린' 7월 개봉</a></span>\n\t</span>","link":"https://kstar.kbs.co.kr/list_view.html?idx=302805","retrieved":1707858095982,"image":"https://entertainimg.kbsmedia.co.kr/cms/uploads/CONTENTS_20240212203531_b214820bd481a5c5f8286592ff5eafa4.png"},{"title":"[리뷰] 살인자ㅇ난감 “난감한 살인자, 난감한 형사, 난감한 넷플릭스”","contents":"<a href=\"https://kstar.kbs.co.kr/list_view.html?idx=302963\">\t<span class=\"img-box hh\">\n\t\t<span class=\"img-thum\">\n\t\t\t<span class=\"img-center\">\n\t\t\t\t<img src=\"https://entertainimg.kbsmedia.co.kr/cms/uploads/CONTENTS_20240213154246_9b26e65150e90b6c78cfe4293a5a40cc.jpg\" alt=\"대체 텍스트\">\n\t\t\t</span>\n\t\t</span>\n\t</span></a>\n\t<span class=\"txt\">\n\t\t<span class=\"max-progtit\"><a href=\"https://kstar.kbs.co.kr/list_view.html?idx=302963\">[리뷰] 살인자ㅇ난감 “난감한 살인자, 난감한 형사, 난감한 넷플릭스” </a></span>\n\t</span>","link":"https://kstar.kbs.co.kr/list_view.html?idx=302963","retrieved":1707807709804,"image":"https://entertainimg.kbsmedia.co.kr/cms/uploads/CONTENTS_20240213154246_9b26e65150e90b6c78cfe4293a5a40cc.jpg"}]}